Workbook

Sheet Resumen
A1: ClothManager – Resumen de APIs
A2: Todos los conteos son fórmulas sobre las hojas 'Inventario APIs' y 'Matriz Componentes'.
A4: Indicador | B4: Valor
A5: Total de APIs | B5: =COUNTA('Inventario APIs'!A5:A112) -> 108
A6: APIs internas | B6: =COUNTIF('Inventario APIs'!C5:C112,"Interna") -> 100
A7: APIs externas | B7: =COUNTIF('Inventario APIs'!C5:C112,"Externa") -> 8
A8: Total de endpoints/métodos definidos | B8: =COUNTA('Matriz Componentes'!A5:A135) -> 131
A9: GET | B9: =COUNTIF('Matriz Componentes'!E5:E135,"GET") -> 56
A10: POST | B10: =COUNTIF('Matriz Componentes'!E5:E135,"POST") -> 41
A11: PUT | B11: =COUNTIF('Matriz Componentes'!E5:E135,"PUT") -> 22
A12: DELETE | B12: =COUNTIF('Matriz Componentes'!E5:E135,"DELETE") -> 12
A13: Endpoints que requieren parámetros | B13: =COUNTIF('Matriz Componentes'!H5:H135,"Sí") -> 131
A14: Endpoints sin parámetros | B14: =COUNTIF('Matriz Componentes'!H5:H135,"No") -> 0
A16: Clasificación funcional
A17: Categoría funcional | B17: N.º de APIs
A18: Consulta | B18: =COUNTIF('Inventario APIs'!D5:D112,A18) -> 40
A19: Transaccional | B19: =COUNTIF('Inventario APIs'!D5:D112,A19) -> 30
A20: Gestión de reservas | B20: =COUNTIF('Inventario APIs'!D5:D112,A20) -> 20
A21: Eventos y sincronización | B21: =COUNTIF('Inventario APIs'!D5:D112,A21) -> 10
A22: Gestión de clientes | B22: =COUNTIF('Inventario APIs'!D5:D112,A22) -> 1
A23: Financiera | B23: =COUNTIF('Inventario APIs'!D5:D112,A23) -> 2
A24: Catálogo e inventario | B24: =COUNTIF('Inventario APIs'!D5:D112,A24) -> 1
A25: Tributaria | B25: =COUNTIF('Inventario APIs'!D5:D112,A25) -> 1
A26: Canal de venta | B26: =COUNTIF('Inventario APIs'!D5:D112,A26) -> 1
A27: Logística | B27: =COUNTIF('Inventario APIs'!D5:D112,A27) -> 1
A28: Recursos humanos | B28: =COUNTIF('Inventario APIs'!D5:D112,A28) -> 1
A29: Total | B29: =SUM(B18:B28) -> 108
A31: Criterio de clasificación
A32: • Internas (10 tipos): Consulta (consultar información, validar disponibilidad, catálogo, saldo) · Transaccional (registrar, actualizar estado, confirmar) · Gestión de reservas (reservar, liberar) · Eventos y sincronización (notificar).
A33: • Externas: se clasifican por el dominio de negocio que integran (financiera, tributaria, logística, canal de venta, etc.).
A34: • Convención de métodos: GET = leer, POST = crear/enviar, PUT = actualizar/confirmar, DELETE = liberar/cancelar/eliminar.
A35: • Endpoints, parámetros y JSON son una propuesta de diseño basada en las Tablas 7 y 8; el documento no los define.

Sheet Inventario APIs
A1: Inventario y clasificación de APIs – ClothManager
A2: Fuente: Tablas 7 y 8 del documento. La categoría funcional y el N.º de métodos son propuesta de diseño.
A4: ID | B4: Nombre | C4: Tipo | D4: Categoría funcional | E4: Módulo solicitante / consumidor | F4: Módulo proveedor / responsable | G4: Propósito | H4: N.º de métodos
A5: API-EXT-001 | B5: API Clientes | C5: Externa | D5: Gestión de clientes | E5: Web / vendedores | F5: MOD-01 Gestión de Pedidos Web | G5: Consultar y registrar información de clientes y direcciones. | H5: =COUNTIF('Matriz Componentes'!$A$5:$A$135,A5) -> 6
A6: API-EXT-002 | B6: API Créditos | C6: Externa | D6: Financiera | E6: Gestión de Pedidos Mayoristas | F6: MOD-07 Gestión de Cartera | G6: Consultar cupo, estado de crédito y restricciones. | H6: =COUNTIF('Matriz Componentes'!$A$5:$A$135,A6) -> 3
A7: API-EXT-003 | B7: API Pagos | C7: Externa | D7: Financiera | E7: Web / POS | F7: MOD-04 Gestión de POS y Facturación | G7: Validar confirmación y resultado de pagos. | H7: =COUNTIF('Matriz Componentes'!$A$5:$A$135,A7) -> 3
A8: API-EXT-004 | B8: API Productos | C8: Externa | D8: Catálogo e inventario | E8: Web / POS / Mayoristas | F8: MOD-02 Gestión de Inventario | G8: Consultar catálogo, variantes, precios y disponibilidad. | H8: =COUNTIF('Matriz Componentes'!$A$5:$A$135,A8) -> 5
A9: API-EXT-005 | B9: API Facturación | C9: Externa | D9: Tributaria | E9: POS / pedidos | F9: MOD-04 Gestión de POS y Facturación | G9: Transmitir documentos electrónicos y consultar su estado. | H9: =COUNTIF('Matriz Componentes'!$A$5:$A$135,A9) -> 3
A10: API-EXT-006 | B10: API WhatsApp | C10: Externa | D10: Canal de venta | E10: Vendedores | F10: MOD-01 Gestión de Pedidos Web | G10: Intercambiar mensajes y datos de pedidos originados por WhatsApp. | H10: =COUNTIF('Matriz Componentes'!$A$5:$A$135,A10) -> 3
A11: API-EXT-007 | B11: API Transporte | C11: Externa | D11: Logística | E11: Despachos | F11: MOD-01 Gestión de Pedidos Web / MOD-06 Gestión de Pedidos Mayoristas | G11: Gestionar guías y consultar estados de entrega. | H11: =COUNTIF('Matriz Componentes'!$A$5:$A$135,A11) -> 3
A12: API-EXT-008 | B12: API Nómina | C12: Externa | D12: Recursos humanos | E12: Administración | F12: MOD-05 Gestión de Nómina y Comisiones | G12: Intercambiar información requerida para procesos de nómina. | H12: =COUNTIF('Matriz Componentes'!$A$5:$A$135,A12) -> 5
A13: API-INT-001 | B13: Consultar información | C13: Interna | D13: Consulta | E13: MOD-01 Gestión de Pedidos Web | F13: MOD-02 Gestión de Inventario | G13: Consultar datos vigentes necesarios para continuar una operación. | H13: =COUNTIF('Matriz Componentes'!$A$5:$A$135,A13) -> 1
A14: API-INT-002 | B14: Validar disponibilidad | C14: Interna | D14: Consulta | E14: MOD-01 Gestión de Pedidos Web | F14: MOD-03 Gestión de Producción | G14: Validar si un recurso, saldo o estado permite continuar. | H14: =COUNTIF('Matriz Componentes'!$A$5:$A$135,A14) -> 1
A15: API-INT-003 | B15: Registrar operación | C15: Interna | D15: Transaccional | E15: MOD-01 Gestión de Pedidos Web | F15: MOD-04 Gestión de POS y Facturación | G15: Registrar una transacción generada por otro módulo. | H15: =COUNTIF('Matriz Componentes'!$A$5:$A$135,A15) -> 1
A16: API-INT-004 | B16: Actualizar estado | C16: Interna | D16: Transaccional | E16: MOD-01 Gestión de Pedidos Web | F16: MOD-05 Gestión de Nómina y Comisiones | G16: Cambiar el estado de una operación relacionada. | H16: =COUNTIF('Matriz Componentes'!$A$5:$A$135,A16) -> 1
... A112: API-INT-100 | B112: Notificar evento | C112: Interna | D112: Eventos y sincronización | E112: MOD-10 Parametrización | F112: MOD-10 Parametrización | G112: Publicar un evento para sincronizar otro módulo. | H112: =COUNTIF('Matriz Componentes'!$A$5:$A$135,A112) -> 1

Sheet Matriz Componentes
A1: Matriz de gestión de componentes (Nombre · Componentes · Parámetros · Métodos)
A2: Propuesta de diseño: el documento no define endpoints. Los componentes usan las 5 capas de la Tabla 6 (API, Application / Service, Domain, Repository, BaseDeDatos).
A4: ID API | B4: Nombre | C4: Tipo | D4: Componentes | E4: Método | F4: Endpoint | G4: Parámetros | H4: ¿Requiere parámetros? | I4: Código de éxito
A5: API-INT-001 | B5: Consultar información (MOD-01 → MOD-02) | C5: Interna | D5: Solicita: Pedidos.Application / Service Provee: Inventario.API → Inventario.Application / Service → Inventario.Domain → Inventario.Repository → Inventario.BaseDeDatos | E5: GET | F5: /api/v1/inventario/consultas | G5: Query: id (string, obligatorio), criterio (string, opcional) | H5: Sí | I5: 200
A6: API-INT-002 | B6: Validar disponibilidad (MOD-01 → MOD-03) | C6: Interna | D6: Solicita: Pedidos.Application / Service Provee: Produccion.API → Produccion.Application / Service → Produccion.Domain → Produccion.Repository → Produccion.BaseDeDatos | E6: GET | F6: /api/v1/produccion/disponibilidad | G6: Query: id (string, obligatorio), cantidad (integer, obligatorio) | H6: Sí | I6: 200
A7: API-INT-003 | B7: Registrar operación (MOD-01 → MOD-04) | C7: Interna | D7: Solicita: Pedidos.Application / Service Provee: POS.API → POS.Application / Service → POS.Domain → POS.Repository → POS.BaseDeDatos | E7: POST | F7: /api/v1/pos-facturacion/operaciones | G7: Body: tipo (string), referencia (string), usuario (string), fecha (datetime), datos (object) | H7: Sí | I7: 201
A8: API-INT-004 | B8: Actualizar estado (MOD-01 → MOD-05) | C8: Interna | D8: Solicita: Pedidos.Application / Service Provee: Nomina.API → Nomina.Application / Service → Nomina.Domain → Nomina.Repository → Nomina.BaseDeDatos | E8: PUT | F8: /api/v1/nomina/operaciones/{id}/estado | G8: Ruta: id (string, obligatorio) Body: estadoAnterior (string), estadoNuevo (string), motivo (string) | H8: Sí | I8: 200
A9: API-INT-005 | B9: Consultar catálogo (MOD-01 → MOD-06) | C9: Interna | D9: Solicita: Pedidos.Application / Service Provee: PedidosMayoristas.API → PedidosMayoristas.Application / Service → PedidosMayoristas.Domain → PedidosMayoristas.Repository → PedidosMayoristas.BaseDeDatos | E9: GET | F9: /api/v1/pedidos-mayoristas/catalogos/{tipo} | G9: Ruta: tipo (string, obligatorio) Query: soloVigentes (boolean, opcional) | H9: Sí | I9: 200
A10: API-INT-006 | B10: Confirmar operación (MOD-01 → MOD-07) | C10: Interna | D10: Solicita: Pedidos.Application / Service Provee: Cartera.API → Cartera.Application / Service → Cartera.Domain → Cartera.Repository → Cartera.BaseDeDatos | E10: PUT | F10: /api/v1/cartera/operaciones/{id}/confirmacion | G10: Ruta: id (string, obligatorio) Body: resultado (string), fecha (datetime) | H10: Sí | I10: 200
A11: API-INT-007 | B11: Consultar saldo (MOD-01 → MOD-08) | C11: Interna | D11: Solicita: Pedidos.Application / Service Provee: Usuarios.API → Usuarios.Application / Service → Usuarios.Domain → Usuarios.Repository → Usuarios.BaseDeDatos | E11: GET | F11: /api/v1/usuarios/saldos/{id} | G11: Ruta: id (string, obligatorio) Query: fecha (date, opcional) | H11: Sí | I11: 200
A12: API-INT-008 | B12: Reservar recurso (MOD-01 → MOD-09) | C12: Interna | D12: Solicita: Pedidos.Application / Service Provee: CostosInsumos.API → CostosInsumos.Application / Service → CostosInsumos.Domain → CostosInsumos.Repository → CostosInsumos.BaseDeDatos | E12: POST | F12: /api/v1/costos-insumos/reservas | G12: Body: recurso (string), cantidad (integer), referencia (string), vigencia (datetime) | H12: Sí | I12: 201
A13: API-INT-009 | B13: Liberar recurso (MOD-01 → MOD-10) | C13: Interna | D13: Solicita: Pedidos.Application / Service Provee: Parametrizacion.API → Parametrizacion.Application / Service → Parametrizacion.Domain → Parametrizacion.Repository → Parametrizacion.BaseDeDatos | E13: DELETE | F13: /api/v1/parametrizacion/reservas/{referencia} | G13: Ruta: referencia (string, obligatorio) Query: motivo (string, obligatorio) | H13: Sí | I13: 204
A14: API-INT-010 | B14: Notificar evento (MOD-01 → MOD-01) | C14: Interna | D14: Solicita: Pedidos.Application / Service Provee: Pedidos.API → Pedidos.Application / Service → Pedidos.Domain → Pedidos.Repository → Pedidos.BaseDeDatos | E14: POST | F14: /api/v1/pedidos-web/eventos | G14: Body: tipoEvento (string), referencia (string), estado (string), marcaTiempo (datetime) | H14: Sí | I14: 202
A15: API-INT-011 | B15: Consultar información (MOD-02 → MOD-01) | C15: Interna | D15: Solicita: Inventario.Application / Service Provee: Pedidos.API → Pedidos.Application / Service → Pedidos.Domain → Pedidos.Repository → Pedidos.BaseDeDatos | E15: GET | F15: /api/v1/pedidos-web/consultas | G15: Query: id (string, obligatorio), criterio (string, opcional) | H15: Sí | I15: 200
A16: API-INT-012 | B16: Validar disponibilidad (MOD-02 → MOD-03) | C16: Interna | D16: Solicita: Inventario.Application / Service Provee: Produccion.API → Produccion.Application / Service → Produccion.Domain → Produccion.Repository → Produccion.BaseDeDatos | E16: GET | F16: /api/v1/produccion/disponibilidad | G16: Query: id (string, obligatorio), cantidad (integer, obligatorio) | H16: Sí | I16: 200
... A135: API-EXT-008 | B135: API Nómina – Consultar liquidación | C135: Externa | D135: Consumidor externo: Administración Nomina.API → Nomina.Application / Service → Nomina.Domain → Nomina.Repository → Nomina.BaseDeDatos | E135: GET | F135: /api/v1/nomina/liquidaciones/{id} | G135: Ruta: id (string, obligatorio) | H135: Sí | I135: 200

Sheet Estructura JSON
A1: Estructura JSON de solicitud (cuerpo) y respuesta – APIs internas y externas
A2: Los valores son ejemplos. Las APIs internas comparten 10 plantillas (una por tipo de comunicación); las externas tienen una fila por endpoint.
A3: Estructura de error común (4xx / 5xx): | C3: { "codigo": "RECURSO_NO_ENCONTRADO", "mensaje": "No existe el recurso solicitado", "detalle": [ { "campo": "id", "error": "valor inexistente" } ], "timestamp": "2026-09-29T10:15:00Z", "traceId": "c1a2b3d4" }
A5: Plantilla / API | B5: Tipo | C5: Nombre | D5: Método y endpoint | E5: Cuerpo de la solicitud (request) | F5: Cuerpo de la respuesta (response) | G5: Código éxito | H5: Errores posibles
A6: API-INT tipo 1 (nº 001, 011, 021, 031, 041, 051, 061, 071, 081, 091) | B6: Interna | C6: Consultar información | D6: GET /api/v1/{modulo}/consultas | E6: Sin cuerpo (parámetros en ruta/query) | F6: { "id": "PED-000123", "criterio": "estado", "datos": [ { "campo": "estado", "valor": "CONFIRMADO", "vigente": true } ], "consultadoEn": "2026-09-29T10:15:00Z" } | G6: 200 | H6: 400, 401, 404, 500
A7: API-INT tipo 2 (nº 002, 012, 022, 032, 042, 052, 062, 072, 082, 092) | B7: Interna | C7: Validar disponibilidad | D7: GET /api/v1/{modulo}/disponibilidad | E7: Sin cuerpo (parámetros en ruta/query) | F7: { "id": "SKU-CAM-001-M", "cantidadSolicitada": 5, "disponible": true, "cantidadDisponible": 42, "estado": "ACTIVO", "resultado": "APROBADO" } | G7: 200 | H7: 400, 401, 404, 500
A8: API-INT tipo 3 (nº 003, 013, 023, 033, 043, 053, 063, 073, 083, 093) | B8: Interna | C8: Registrar operación | D8: POST /api/v1/{modulo}/operaciones | E8: { "tipo": "VENTA_POS", "referencia": "FAC-000456", "usuario": "vendedor01", "fecha": "2026-09-29T10:15:00Z", "datos": { "total": 250000, "moneda": "COP" } } | F8: { "id": "OP-000789", "referencia": "FAC-000456", "estado": "REGISTRADA", "fechaRegistro": "2026-09-29T10:15:02Z" } | G8: 201 | H8: 400, 401, 409, 422, 500
A9: API-INT tipo 4 (nº 004, 014, 024, 034, 044, 054, 064, 074, 084, 094) | B9: Interna | C9: Actualizar estado | D9: PUT /api/v1/{modulo}/operaciones/{id}/estado | E9: { "estadoAnterior": "PAGADO", "estadoNuevo": "EN_PREPARACION", "motivo": "Pedido enviado a bodega" } | F9: { "id": "PED-000123", "estado": "EN_PREPARACION", "actualizadoEn": "2026-09-29T10:20:00Z" } | G9: 200 | H9: 400, 401, 404, 409, 422, 500
A10: API-INT tipo 5 (nº 005, 015, 025, 035, 045, 055, 065, 075, 085, 095) | B10: Interna | C10: Consultar catálogo | D10: GET /api/v1/{modulo}/catalogos/{tipo} | E10: Sin cuerpo (parámetros en ruta/query) | F10: { "tipo": "TIPO_DOCUMENTO", "items": [ { "codigo": "CC", "descripcion": "Cédula de ciudadanía", "atributos": { "longitudMax": 10 }, "vigente": true, "vigenciaDesde": "2020-01-01" } ] } | G10: 200 | H10: 400, 401, 404, 500
A11: API-INT tipo 6 (nº 006, 016, 026, 036, 046, 056, 066, 076, 086, 096) | B11: Interna | C11: Confirmar operación | D11: PUT /api/v1/{modulo}/operaciones/{id}/confirmacion | E11: { "resultado": "EXITOSO", "fecha": "2026-09-29T10:25:00Z" } | F11: { "id": "OP-000789", "confirmada": true, "resultado": "EXITOSO", "fecha": "2026-09-29T10:25:00Z" } | G11: 200 | H11: 400, 401, 404, 409, 500
A12: API-INT tipo 7 (nº 007, 017, 027, 037, 047, 057, 067, 077, 087, 097) | B12: Interna | C12: Consultar saldo | D12: GET /api/v1/{modulo}/saldos/{id} | E12: Sin cuerpo (parámetros en ruta/query) | F12: { "id": "CLI-0045", "saldo": 1500000, "cupo": 5000000, "moneda": "COP", "fechaConsulta": "2026-09-29T10:30:00Z" } | G12: 200 | H12: 400, 401, 404, 500
A13: API-INT tipo 8 (nº 008, 018, 028, 038, 048, 058, 068, 078, 088, 098) | B13: Interna | C13: Reservar recurso | D13: POST /api/v1/{modulo}/reservas | E13: { "recurso": "SKU-CAM-001-M", "cantidad": 5, "referencia": "PED-000123", "vigencia": "2026-09-29T11:15:00Z" } | F13: { "reservaId": "RES-000001", "estado": "RESERVADA", "vigenteHasta": "2026-09-29T11:15:00Z" } | G13: 201 | H13: 400, 401, 409, 422, 500
A14: API-INT tipo 9 (nº 009, 019, 029, 039, 049, 059, 069, 079, 089, 099) | B14: Interna | C14: Liberar recurso | D14: DELETE /api/v1/{modulo}/reservas/{referencia} | E14: Sin cuerpo (parámetros en ruta/query) | F14: Sin cuerpo (204 No Content) | G14: 204 | H14: 400, 401, 404, 500
A15: API-INT tipo 10 (nº 010, 020, 030, 040, 050, 060, 070, 080, 090, 100) | B15: Interna | C15: Notificar evento | D15: POST /api/v1/{modulo}/eventos | E15: { "tipoEvento": "PEDIDO_CONFIRMADO", "referencia": "PED-000123", "estado": "CONFIRMADO", "marcaTiempo": "2026-09-29T10:35:00Z" } | F15: { "eventoId": "EVT-000001", "estado": "ENCOLADO" } | G15: 202 | H15: 400, 401, 422, 500
A16: API-EXT-001 | B16: Externa | C16: API Clientes – Consultar cliente | D16: GET /api/v1/clientes/{id} | E16: Sin cuerpo (parámetros en ruta/query) | F16: { "id": "CLI-0045", "tipoDocumento": "CC", "documento": "1098765432", "nombre": "María Pérez", "correo": "maria@correo.com", "telefono": "3001234567", "direcciones": [ { "id": "DIR-01", "ciudad": "Bucaramanga", "direccion": "Cra 27 # 45-10" } ] } | G16: 200 | H16: 401, 404, 500
A17: API-EXT-001 | B17: Externa | C17: API Clientes – Buscar clientes | D17: GET /api/v1/clientes | E17: Sin cuerpo (parámetros en ruta/query) | F17: { "pagina": 1, "total": 1, "items": [ { "id": "CLI-0045", "nombre": "María Pérez", "documento": "1098765432" } ] } | G17: 200 | H17: 400, 401, 500
... A46: API-EXT-008 | B46: Externa | C46: API Nómina – Consultar liquidación | D46: GET /api/v1/nomina/liquidaciones/{id} | E46: Sin cuerpo (parámetros en ruta/query) | F46: { "liquidacionId": "LIQ-202609", "periodo": "2026-09", "estado": "CALCULADA", "totalNomina": 38500000, "moneda": "COP" } | G46: 200 | H46: 401, 404, 500
